lib221321GI/__init__.py
lib221321GI/database.py
lib221321GI-0.1.dist-info/METADATA
lib221321GI-0.1.dist-info/WHEEL
lib221321GI-0.1.dist-info/top_level.txt
lib221321GI-0.1.dist-info/RECORD
