Metadata-Version: 2.1
Name: lib221321GI
Version: 0.1
Summary: A library for interacting with a PostgreSQL database
Author: Sidezi
Author-email: gus3viw@yandex.ru
Classifier: Programming Language :: Python :: 3
Classifier: License :: OSI Approved :: MIT License
Classifier: Operating System :: OS Independent
Requires-Python: >=3.6
Requires-Dist: psycopg2
